ticgen
