Metadata-Version: 1.1
Name: ticgen
Version: 1.0.4
Summary: Calculate TESS noise level and TESS magnitude.
Home-page: https://github.com/tessgi/ticgen
Author: Tom Barclay
Author-email: tom@tombarclay.com
License: MIT
Platform: UNKNOWN
Classifier: Development Status :: 5 - Production/Stable
Classifier: License :: OSI Approved :: MIT License
Classifier: Operating System :: OS Independent
Classifier: Programming Language :: Python
Classifier: Intended Audience :: Science/Research
Classifier: Topic :: Scientific/Engineering :: Astronomy
